CHANGELOG.md
werkit/__init__.py
werkit/aws_lambda/__init__.py
werkit/aws_lambda/build.py
werkit/aws_lambda/deploy.py
werkit/common/cli_common.py
werkit/compute/__init__.py
werkit/compute/_destination.py
werkit/compute/_formatting.py
werkit/compute/_manager.py
werkit/compute/_schema.py
werkit/compute/_serialization.py
werkit/compute/_synthetic_error.py
werkit/compute/_types.py
werkit/compute/destination/lambda_destination.py
werkit/compute/destination/rds_graphile_worker.py
werkit/compute/generated/manager_testing.schema.json
werkit/compute/graph/README.md
werkit/compute/graph/__init__.py
werkit/compute/graph/_binding.py
werkit/compute/graph/_built_in_type.py
werkit/compute/graph/_custom_type.py
werkit/compute/graph/_dependency_graph.py
werkit/compute/graph/_state_manager.py
werkit/compute/graph/dependency-graph.schema.json
werkit/compute/graph/generated/schema.json
werkit/compute/graph/schema.ts
werkit/compute/graph/testing_examples.py
werkit/compute/manager_testing.schema.ts
werkit/orchestrator/__init__.py
werkit/orchestrator/deploy.py
werkit/orchestrator/orchestrator_lambda/__init__.py
werkit/orchestrator/orchestrator_lambda/generated/schema.json
werkit/orchestrator/orchestrator_lambda/handler.py
werkit/orchestrator/orchestrator_lambda/parallel.py
werkit/orchestrator/orchestrator_lambda/schema.py
werkit/orchestrator/orchestrator_lambda/schema.ts
werkit/orchestrator/testing/__init__.py
werkit/orchestrator/testing/worker_service/__init__.py
werkit/orchestrator/testing/worker_service/generated/schema.json
werkit/orchestrator/testing/worker_service/handler.py
werkit/orchestrator/testing/worker_service/schema.ts
werkit/publish_to_s3.py
werkit/py.typed
werkit/s3.py
werkit/scripts/publish_to_s3.py
werkit-0.36.0.dist-info/LICENSE
werkit-0.36.0.dist-info/WHEEL
werkit-0.36.0.dist-info/METADATA
werkit-0.36.0.dist-info/RECORD
